loomdots/__init__.py
loomdots/expose.py
loomdots/introspection.py
loomdots/server.py
loomdots/validation.py
loomdots/wrappers.py
loomdots-0.1.0.post1.dist-info/METADATA
loomdots-0.1.0.post1.dist-info/WHEEL
loomdots-0.1.0.post1.dist-info/RECORD
