Metadata-Version: 2.4
Name: loomdots
Version: 0.1.0.post1
Summary: The network layer for agents.
Requires-Python: <3.13,>=3.10
Requires-Dist: a2a-sdk[http-server]>=0.1.0
Requires-Dist: psutil>=5.9.0
Requires-Dist: sse-starlette>=2.1.0
Requires-Dist: starlette>=0.37.2
Requires-Dist: uvicorn>=0.24.0
Provides-Extra: dev
Requires-Dist: coverage[toml]>=7.3.0; extra == 'dev'
Requires-Dist: pytest-asyncio>=0.21.0; extra == 'dev'
Requires-Dist: pytest-mock>=3.11.0; extra == 'dev'
Requires-Dist: pytest>=8.3.2; extra == 'dev'
Requires-Dist: ruff>=0.5.6; extra == 'dev'
Provides-Extra: framework-support
Requires-Dist: google-adk>=0.1.0; extra == 'framework-support'
